{
  "_doc": "Subset PÚBLICO de fenix_state.json · só campos renderizados pelo dashboard.html/monitor.html · gerado por dashboard_publisher.py",
  "ultimo_update": "11/06/2026 21:49:32",
  "last_github_push": "11/06 21:49",
  "last_github_push_ts": 1781228972.123939,
  "baseline": {
    "data": "2026-04-27",
    "pnl_acumulado": -6124.0,
    "metrica_oficial": "cumRealisedPnl da conta UNIFIED USDT na Bybit"
  },
  "saldo": {
    "cum_realised_pnl": -6841.35,
    "cumPnL_unified_usd": -6841.35,
    "unrealisedPnl": 0.0,
    "ts": "2026-06-02T20:05:00-04:00",
    "progresso_vs_baseline_usd": -717.35,
    "delta_vs_baseline": -717.35,
    "pnl_fenix_desde_baseline": -717.35,
    "updated_at": "2026-06-11T21:49:31-04:00"
  },
  "progresso_vs_baseline": {
    "baseline_pnl": -6124.0,
    "current_pnl": -6841.35,
    "diff_usd": -717.35
  },
  "posicao_atual": {
    "side": "NONE",
    "size": 0,
    "qty": 0,
    "avgPrice": 63151.92564503,
    "avg_price": 63151.92564503,
    "entry_price": 63151.92564503,
    "stopLoss": 61671.4,
    "stop_loss": 61671.4,
    "takeProfit": 69355.1,
    "take_profit": 69355.1,
    "tp2": 69355.1,
    "tp1": null,
    "tp1_limit": null,
    "tp1_pnl_lock": 0,
    "tp1_realizado": false,
    "status": "OPEN_LONG",
    "markPrice": 62715.7,
    "mark_price_atual": 62715.7,
    "unrealised_pnl_usd": 0,
    "unrealisedPnl": -336.77,
    "be_price": 63574.44877265,
    "liq_price": 59238.0,
    "tp2_target_estrutural": 69355.1,
    "last_update": "2026-06-11T08:25:12-04:00",
    "ts_snapshot": "2026-06-11T21:49:32-04:00"
  },
  "trades_recentes": [],
  "current_thesis": {
    "thesis_id": "boot_d_close_2026-06-11_WAVE_C_DOWN_C1fundo_59081_C2corretivaUP_bullreversal_63600_SHORTtopo_AUTONOMA",
    "boot_ts": "2026-06-11T20:18:00-04:00",
    "ultimo_update": "2026-06-11T21:45:00-04:00",
    "status": "ACTIVE",
    "mark_at_boot": 63600.0,
    "mark_now": 63466.2,
    "macro_bias_D": {
      "direcao": "BEARISH",
      "score": 8.0
    },
    "leitura_primaria_opus": "D-0 (11/06) fechou 63600 (+3,45% vs D-1) · candle BULL REVERSAL (O 61476 H 63900 L 61476 C 63600), high 63900 capado sob 64250, vol 80,6k BTC. RSI diario 31,2 (saindo da sobrevenda extrema), preco abaixo EMA9 ~63800 e EMA20 67213 descendente, MACD hist -4032 achatando. 4H RSI 59,4 acima EMA9/20, MACD +390 hist+140 (bounce); 1H RSI 61,9 acima EMA9/20/50 (impulso de alivio); 15m coil/compressao. Estrutura macro INALTERADA: ABC zigzag bearish, WAVE C DOWN. C-1 completou em 59081, C-2 corretiva UP em andamento, retracou so ~20% da C-1 (bounce jovem). Diario macro down + 4H/1H bounce = C-2 corretiva tipica. Niveis-chave: today_low 61476 (perder em close 4H = C-3 cedo), invalidacao B/macro em close D > 82811. Funding +0,0086% (leve premio long), OI +3% (longs entrando no bounce), L/S 0,605 crowded long, ask wall 5,2 BTC em 63574. AUTONOMIA RESTAURADA 11/06: FÊNIX opera dentro da LEI (open/manage/close) · FLAT no momento, sem trade abaixo da zona de short.",
    "cenarios_opus": {
      "cenario_A_C2_estende_zona_SHORT": {
        "prob": 0.55,
        "entry": "66700-68150",
        "sl": 69600,
        "tp1": 60700,
        "tp2": 57500,
        "rr": 4.2,
        "note": "C-2 estende ate a zona de retracement Fib da C-1 (0,236=64682 piso ate 0,382=68146 topo). E onde arma o SHORT macro (Espinha plan). Exige romper 64250 com volume e alcancar 64.7-68.1k. Topo da C-2 = entrada SHORT na exaustao (rejeicao 5m). Queda C-3 -> alvos 57499/49680."
      },
      "cenario_B_C2_rasa_C3_cedo": {
        "prob": 0.3,
        "entry": null,
        "sl": null,
        "tp1": null,
        "tp2": null,
        "rr": null,
        "note": "C-2 ja topou rasa (~64250, so 0.236 da C-1, bounce fraco) · C-3 down retoma cedo SEM arme em 63,5k (LEI #28 veta short abaixo da zona). Gatilho: close 4H < 61476 (today_low) -> perde 60705 -> 59081. close 1H < 59081 = C-3 down confirmada. FÊNIX nao shorta aqui (fora de zona) · espera retest da zona OU breakdown limpo."
      },
      "cenario_C_corre_zona_estendida": {
        "prob": 0.15,
        "entry": "70946-73746",
        "sl": 77733,
        "tp1": 65000,
        "tp2": 57500,
        "rr": 2.0,
        "note": "C-2 corre direto ate 0,5=70946 / 0,618=73746 da C-1 (extensao). Arma SHORT estendido (Tier menor, contagem mais esticada). Invalida onda em close > 74310 (recount Espinha)."
      }
    },
    "setups_pre_armados": [
      {
        "tipo": "SHORT_topo_C2_macro",
        "lado": "SHORT",
        "direcao": "SHORT",
        "entry_zone": "67800-68146",
        "entry": 68146,
        "sl": 68800,
        "tp1": 60700,
        "tp2": 57500,
        "rr": 16.3,
        "qty_btc": 0.26,
        "tier": "T3",
        "macro_aligned": true,
        "invalidacao": "close 1H > 69600 (acima 1,272A/zona) ou recount Espinha close > 74310",
        "razao_estrutural": "SHORT no topo da C-2 (Fib 0,382 da C-1 = 68146). T3 porque eh a-FAVOR do macro down e mira a C-3 (onda impulsiva de maior conviccao). VENDER ALTO (67500-68150) com SL tight 69200 (~1,5%) viabiliza T3 dentro da regra de distancia do SL. Se C-2 estender alem de 0,382 e stopar, o setup estendido (70946-73746) re-shorta no 0,5/0,618. Gatilho: exaustao/rejeicao no 5m na zona alta. AUTONOMA (LEI #28/#29 OK).",
        "ordem_pronta": {
          "category": "linear",
          "symbol": "BTCUSDT",
          "side": "Sell",
          "orderType": "Limit",
          "price": "68146",
          "qty": "0.260",
          "orderLinkId": "fenix_short_c2topo_ellstruct",
          "stopLoss": "68800",
          "takeProfit": "60700",
          "tpslMode": "Partial",
          "tpSize": "0.080"
        },
        "guards_verificados": "8/8 green 11/06 21:45 · entry_guard caminho C1 (_ellstruct + manual_override fresco) · params B7 risco 5,8%<6%"
      },
      {
        "tipo": "SHORT_topo_C2_estendido",
        "lado": "SHORT",
        "direcao": "SHORT",
        "entry_zone": "70946-73746",
        "entry": 70946,
        "sl": 77733,
        "tp1": 65000,
        "tp2": 57500,
        "rr": 2.0,
        "qty_btc": 0.185,
        "tier": "T2",
        "macro_aligned": true,
        "invalidacao": "close > 74310 (recount onda)",
        "razao_estrutural": "Extensao da zona SHORT caso a C-2 estenda ate 0,5/0,618 da C-1 (70946/73746). Tier T2 (regra user: trade a-favor da tendencia NUNCA T1). AUTONOMA: arma e executa na exaustao confirmada (LEI #28/#29 OK)."
      }
    ],
    "ponto_nao_retorno": "BEAR MACRO invalida TOTAL: close D > 82811 (topo B). ONDA invalida (recount Espinha · topo C-2 estourou): close > 74310 (teto onda-2/C). C-3 cedo (C-2 topou rasa): close 4H < 61476 (today_low) -> perde 60705 -> close 1H < 59081 (extremo C-1) = C-3 down confirmada. Suporte: PP D 62992 · S1 D 62084 · S2 D 60569 · 59081 (extremo C-1). Resistencia: R1 D 64508 · 64250 (topo C-2 spike) · 64682 (0,236 C-1 = piso zona short) · 68146 (0,382 · topo zona short primaria) · 70946 (0,5) · 73746 (0,618).",
    "proximo_marco": "Close 4H 22:00 UTC-4 · depois close 1H sequencial. Decide se a C-2 estende ate a zona SHORT 64.7-68.1k (cenario A · arma short na exaustao) vs topou rasa e C-3 retoma cedo (B · breakdown <61476) vs corre 70.9-73.7k (C). AUTONOMIA RESTAURADA: FÊNIX opera dentro da LEI · FLAT agora · entry autonomo so em zona pre-armada (LEI #28) na exaustao do topo C-2."
  },
  "execution_mode": "AUTO",
  "manual_approval_required": true,
  "price_watch": {
    "ts": "2026-06-11T21:05:00-04:00",
    "levels": [
      {
        "price": 82811,
        "direction": "above",
        "tier": "alto",
        "reason": "topo B · INVALIDACAO TOTAL bear macro (close D)",
        "decisao_pre_armada": "SE close D > 82811: tese ABC bearish MORRE · disparar skill fenix-analise-macro + RECOUNT Espinha. AUTONOMA: re-valida e executa/documenta dentro da LEI.",
        "active": true,
        "triggered": false
      },
      {
        "price": 74310,
        "direction": "above",
        "tier": "alto",
        "reason": "teto onda-2/C · INVALIDACAO ONDA (recount)",
        "decisao_pre_armada": "SE close > 74310: C-2 estourou o teto · forcar RECOUNT Espinha (limpar lock tree.json). AUTONOMA: re-valida e executa/documenta dentro da LEI.",
        "active": true,
        "triggered": false
      },
      {
        "price": 73746,
        "direction": "above",
        "tier": "medio",
        "reason": "Fib 0.618 C-1 · teto ALTO da zona SHORT (cenario B estendido)",
        "decisao_pre_armada": "Topo extremo da C-2. SE bounce reverter no 5m aqui = SHORT macro (setup secundario). AUTONOMA: re-valida (score+R:R+Espinha) e executa/documenta.",
        "active": true,
        "triggered": false
      },
      {
        "price": 70946,
        "direction": "above",
        "tier": "medio",
        "reason": "Fib 0.5 C-1 · zona SHORT estendida",
        "decisao_pre_armada": "Meio da zona SHORT estendida (setup 2 entry). AUTONOMA: re-valida (score+R:R+Espinha) e executa/documenta.",
        "active": true,
        "triggered": false
      },
      {
        "price": 68146,
        "direction": "above",
        "tier": "alto",
        "reason": "Fib 0.382 C-1 · TOPO da zona SHORT primaria",
        "decisao_pre_armada": "Topo da zona SHORT primaria (setup 1). SE exaustao/rejeicao 5m = ponto de SHORT macro. AUTONOMA: re-valida (score+R:R+Espinha) e executa/documenta.",
        "active": true,
        "triggered": false
      },
      {
        "price": 64682,
        "direction": "above",
        "tier": "alto",
        "reason": "Fib 0.236 C-1 (64682) ~ R1 D · PISO da zona SHORT primaria",
        "decisao_pre_armada": "Piso da zona SHORT primaria + entrada na C-2 estendida. SE chegar = vigiar exaustao 5m. AUTONOMA: re-valida (score+R:R+Espinha) e executa/documenta.",
        "active": true,
        "triggered": false
      },
      {
        "price": 64250,
        "direction": "above",
        "tier": "alto",
        "reason": "topo C-2 (spike 06/06 + rejeicao 64220 08/06) ~ topo A",
        "decisao_pre_armada": "Topo da perna A da C-2. Romper com volume = C-2 estende pra zona SHORT; rejeitar = C-2 topou (cenario A). AUTONOMA: re-valida e executa/documenta dentro da LEI.",
        "active": true,
        "triggered": false
      },
      {
        "price": 61476,
        "direction": "below",
        "tier": "alto",
        "reason": "today_low 11/06 (low do D-0 bull reversal) · perda em close 4H = C-2 topou rasa, C-3 cedo",
        "decisao_pre_armada": "AUTONOMA. SE close 4H/1H < 61476: C-2 provavelmente topou rasa (so 0.236 C-1) · C-3 down retoma rumo 60705 -> 59081. Re-valida Espinha · sem short autonomo abaixo de 64.7k (LEI #28 fora de zona) · documentar e vigiar breakdown limpo p/ retest da zona.",
        "active": true,
        "triggered": false
      }
    ]
  },
  "monitor_url": "https://exclusion-comes-encoding-archive.trycloudflare.com"
}